supersk_sphinx_bulma/__init__.py
supersk_sphinx_bulma/_version.py
supersk_sphinx_bulma/layout.html
supersk_sphinx_bulma/navbar.html
supersk_sphinx_bulma/searchbox.html
supersk_sphinx_bulma/theme.conf
supersk_sphinx_bulma/static/bulma.css
supersk_sphinx_bulma/static/custom.js
supersk_sphinx_bulma/static/made-with-bulma.png
supersk_sphinx_bulma/static/supersk-sphinx-bulma.css
supersk_sphinx_bulma-0.1.0.dist-info/LICENSE
supersk_sphinx_bulma-0.1.0.dist-info/METADATA
supersk_sphinx_bulma-0.1.0.dist-info/WHEEL
supersk_sphinx_bulma-0.1.0.dist-info/entry_points.txt
supersk_sphinx_bulma-0.1.0.dist-info/top_level.txt
supersk_sphinx_bulma-0.1.0.dist-info/RECORD
